<?xml version="1.0" ?><FindBugsFilter><Match><Bug pattern="AOM_ABSTRACT_OVERRIDDEN_METHOD"></Bug></Match><Match><Bug pattern="PCOA_PARTIALLY_CONSTRUCTED_OBJECT_ACCESS"></Bug></Match><Match><Bug pattern="XSS_JSP_PRINT"></Bug></Match><Match><Bug pattern="JSP_JSTL_OUT"></Bug></Match><Match><Bug pattern="JSP_INCLUDE"></Bug></Match><Match><Bug pattern="JSP_XSLT"></Bug></Match><Match><Bug pattern="XSS_REQUEST_PARAMETER_TO_JSP_WRITER"></Bug></Match><Match><Bug pattern="JSP_SPRING_EVAL"></Bug></Match><Match><Bug pattern="NM_LCASE_HASHCODE"></Bug></Match><Match><Bug pattern="EQ_ALWAYS_TRUE"></Bug></Match><Match><Bug pattern="EC_UNRELATED_CLASS_AND_INTERFACE"></Bug></Match><Match><Bug pattern="RANGE_ARRAY_INDEX"></Bug></Match><Match><Bug pattern="CN_IMPLEMENTS_CLONE_BUT_NOT_CLONEABLE"></Bug></Match><Match><Bug pattern="EC_NULL_ARG"></Bug></Match><Match><Bug pattern="NM_BAD_EQUAL"></Bug></Match><Match><Bug pattern="NM_METHOD_CONSTRUCTOR_CONFUSION"></Bug></Match><Match><Bug pattern="NP_EQUALS_SHOULD_HANDLE_NULL_ARGUMENT"></Bug></Match><Match><Bug pattern="NM_LCASE_TOSTRING"></Bug></Match><Match><Bug pattern="EQ_ALWAYS_FALSE"></Bug></Match><Match><Bug pattern="RANGE_ARRAY_LENGTH"></Bug></Match><Match><Bug pattern="BC_IMPOSSIBLE_INSTANCEOF"></Bug></Match><Match><Bug pattern="HE_HASHCODE_NO_EQUALS"></Bug></Match><Match><Bug pattern="MF_CLASS_MASKS_FIELD"></Bug></Match><Match><Bug pattern="HE_EQUALS_USE_HASHCODE"></Bug></Match><Match><Bug pattern="NM_CLASS_NAMING_CONVENTION"></Bug></Match><Match><Bug pattern="NM_FIELD_NAMING_CONVENTION"></Bug></Match><Match><Bug pattern="NM_METHOD_NAMING_CONVENTION"></Bug></Match><Match><Bug pattern="NM_CLASS_NOT_EXCEPTION"></Bug></Match></FindBugsFilter>